mysvr-1.0.0.dist-info/DESCRIPTION.rst
mysvr-1.0.0.dist-info/METADATA
mysvr-1.0.0.dist-info/RECORD
mysvr-1.0.0.dist-info/WHEEL
mysvr-1.0.0.dist-info/metadata.json
mysvr-1.0.0.dist-info/top_level.txt
svr/L2.py
svr/SV.py
svr/__init__.py
svr/kernelfunc.py
svr/examples/1d_svr.py
svr/examples/__init__.py
